dexterity.membrane-3.0.1-py3.11-nspkg.pth
dexterity/membrane/__init__.py
dexterity/membrane/configure.zcml
dexterity/membrane/deprecation.py
dexterity/membrane/indexers.py
dexterity/membrane/membrane_helpers.py
dexterity/membrane/rebuild_i18n.sh
dexterity/membrane/testing.py
dexterity/membrane/behavior/__init__.py
dexterity/membrane/behavior/configure.zcml
dexterity/membrane/behavior/group.py
dexterity/membrane/behavior/membranegroup.py
dexterity/membrane/behavior/membranepassword.py
dexterity/membrane/behavior/membraneuser.py
dexterity/membrane/behavior/password.py
dexterity/membrane/behavior/settings.py
dexterity/membrane/behavior/user.py
dexterity/membrane/content/__init__.py
dexterity/membrane/content/configure.zcml
dexterity/membrane/content/member.py
dexterity/membrane/locales/dexterity.membrane.pot
dexterity/membrane/locales/manual.pot
dexterity/membrane/locales/plone.pot
dexterity/membrane/locales/en/LC_MESSAGES/dexterity.membrane.mo
dexterity/membrane/locales/en/LC_MESSAGES/dexterity.membrane.po
dexterity/membrane/locales/en/LC_MESSAGES/plone.mo
dexterity/membrane/locales/en/LC_MESSAGES/plone.po
dexterity/membrane/locales/es/LC_MESSAGES/dexterity.membrane.mo
dexterity/membrane/locales/es/LC_MESSAGES/dexterity.membrane.po
dexterity/membrane/locales/es/LC_MESSAGES/plone.mo
dexterity/membrane/locales/es/LC_MESSAGES/plone.po
dexterity/membrane/locales/fr/LC_MESSAGES/dexterity.membrane.mo
dexterity/membrane/locales/fr/LC_MESSAGES/dexterity.membrane.po
dexterity/membrane/locales/nl/LC_MESSAGES/dexterity.membrane.mo
dexterity/membrane/locales/nl/LC_MESSAGES/dexterity.membrane.po
dexterity/membrane/locales/nl/LC_MESSAGES/plone.mo
dexterity/membrane/locales/nl/LC_MESSAGES/plone.po
dexterity/membrane/locales/pt_BR/LC_MESSAGES/dexterity.membrane.mo
dexterity/membrane/locales/pt_BR/LC_MESSAGES/dexterity.membrane.po
dexterity/membrane/locales/pt_BR/LC_MESSAGES/plone.mo
dexterity/membrane/locales/pt_BR/LC_MESSAGES/plone.po
dexterity.membrane-3.0.1.dist-info/METADATA
dexterity.membrane-3.0.1.dist-info/WHEEL
dexterity.membrane-3.0.1.dist-info/entry_points.txt
dexterity.membrane-3.0.1.dist-info/namespace_packages.txt
dexterity.membrane-3.0.1.dist-info/top_level.txt
dexterity.membrane-3.0.1.dist-info/RECORD
