Metadata-Version: 2.1
Name: dexterity.membrane
Version: 3.0.1
Summary: Dexterity content and behaviors to integrate with membrane.
Home-page: https://github.com/collective/dexterity.membrane
Author: Maurits van Rees
Author-email: maurits@vanrees.org
License: GPL
Keywords: plone dexterity membrane
Classifier: Development Status :: 5 - Production/Stable
Classifier: Environment :: Web Environment
Classifier: Framework :: Plone :: Addon
Classifier: Framework :: Plone :: 5.2
Classifier: Framework :: Plone :: 6.0
Classifier: Framework :: Plone
Classifier: Intended Audience :: System Administrators
Classifier: License :: OSI Approved :: GNU General Public License v2 (GPLv2)
Classifier: Operating System :: OS Independent
Classifier: Programming Language :: Python :: 3.6
Classifier: Programming Language :: Python :: 3.7
Classifier: Programming Language :: Python :: 3.8
Classifier: Programming Language :: Python :: 3.9
Classifier: Programming Language :: Python :: 3.10
Classifier: Programming Language :: Python :: 3.11
Classifier: Programming Language :: Python
Classifier: Topic :: Software Development :: Libraries :: Python Modules
Requires-Python: >=3.6
Requires-Dist: Products.CMFPlone (>=5.2)
Requires-Dist: Products.membrane
Requires-Dist: bcrypt (>=2.0)
Requires-Dist: plone.api
Requires-Dist: plone.app.dexterity
Requires-Dist: plone.memoize
Requires-Dist: setuptools
Requires-Dist: zope.deprecation
Provides-Extra: archetypes
Requires-Dist: plone.app.referenceablebehavior (>=0.7.0) ; extra == 'archetypes'
Provides-Extra: test
Requires-Dist: plone.app.testing ; extra == 'test'
